{"text": "that the souls of the good dwell in the forms of white birds, under the throne\nof GOD.3 As to the condition of the souls of the wicked, besides the opinions\nthat have been already mentioned, the more orthodox hold that they are offered\nby the angels to heaven, from whence being repulsed as stinking and filthy,\nthey are offered to the earth, and being also refused a place there, are\ncarried down to the seventh earth, and being also refused a place there, are\ncarried down to the seventh earth, and thrown into a dungeon, which they call\nSajîn, under a green rock, or according to a tradition of Mohammed, under the\ndevil's jaw,4 to be there tormented, till they are called up to be joined\nagain to their bodies.\n Though some among the Mohammedans have thought that the resurrection will\nbe merely spiritual, and no more than the returning of the soul to the place\nwhence it first came (an opinion defended by Ebn Sina,5 and called by some the\nopinion of the philosophers6); and others, who allow man to consist of body\n", "model_name": "sentence-transformers/paraphrase-multilingual-MiniLM-L12-v2", "chunking_name": "paragraph", "chunk_size": 1024, "chunk_overlap": 128}