{"text": "Then Drances took the word, who grudg’d, long since,\n The rising glories of the Daunian prince.\n Factious and rich, bold at the council board,\n But cautious in the field, he shunn’d the sword;\n A close caballer, and tongue-valiant lord.\n Noble his mother was, and near the throne;\n But, what his father’s parentage, unknown.\n He rose, and took th’ advantage of the times,\n To load young Turnus with invidious crimes.\n “Such truths, O king,” said he, “your words contain,\n As strike the sense, and all replies are vain;\n Nor are your loyal subjects now to seek\n What common needs require, but fear to speak.\n Let him give leave of speech, that haughty man,\n Whose pride this unauspicious war began;\n For whose ambition (let me dare to say,\n Fear set apart, tho’ death is in my way)\n The plains of Latium run with blood around.\n So many valiant heroes bite the ground;\n Dejected grief in ev’ry face appears;\n A town in mourning, and a land in tears;\n While he, th’ undoubted author of our harms,\n", "model_name": "intfloat/e5-large-v2", "chunking_name": "paragraph", "chunk_size": 1024, "chunk_overlap": 128}