{"text": "32:9 And the LORD said unto Moses, I have seen this people, and,\nbehold, it is a stiffnecked people: 32:10 Now therefore let me alone,\nthat my wrath may wax hot against them, and that I may consume them:\nand I will make of thee a great nation.\n\n32:11 And Moses besought the LORD his God, and said, LORD, why doth\nthy wrath wax hot against thy people, which thou hast brought forth\nout of the land of Egypt with great power, and with a mighty hand?\n32:12 Wherefore should the Egyptians speak, and say, For mischief did\nhe bring them out, to slay them in the mountains, and to consume them\nfrom the face of the earth? Turn from thy fierce wrath, and repent of\nthis evil against thy people.\n\n32:13 Remember Abraham, Isaac, and Israel, thy servants, to whom thou\nswarest by thine own self, and saidst unto them, I will multiply your\nseed as the stars of heaven, and all this land that I have spoken of\nwill I give unto your seed, and they shall inherit it for ever.", "model_name": "sentence-transformers/paraphrase-multilingual-MiniLM-L12-v2", "chunking_name": "paragraph", "chunk_size": 1024, "chunk_overlap": 128}