{"text": "the expedition of Tabûc, with a design to hinder Mohammed's men from engaging\ntherein; and when he was asked to pray there, he answered that he was just\nsetting out on a journey, but that when he came back, with GOD'S leave, he\nwould do what they desired; but when they applied to him again, on his return,\nthis passage was revealed.1\n x That is, Abu Amer, the monk, who was a declared enemy to Mohammed,\nhaving threatened him at Ohod, that no party should appear in the field\nagainst him, but he would make one of them; and, to be as good as his word, he\ncontinued to oppose him till the battle of Honein, at which he was present,\nand being put to flight with those of Hawâzen, he retreated into Syria,\ndesigning to obtain a supply of troops from the Grecian emperor to renew the\nwar, but he died at Kinnisrîn. Others say that this monk was a confederate at\nthe war of the ditch, and that he fled thence into Syria.2\n y viz., That of Kobâ, a place about two miles from Medina, where\n", "model_name": "BAAI/bge-m3", "chunking_name": "paragraph", "chunk_size": 1024, "chunk_overlap": 128}