{"text": "Thus did they converse; meanwhile Melanthius the goatherd came up, for\nhe too was bringing in his best goats for the suitors’ dinner; and he\nhad two shepherds with him. They tied the goats up under the gatehouse,\nand then Melanthius began gibing at Ulysses. “Are you still here,\nstranger,” said he, “to pester people by begging about the house? Why\ncan you not go elsewhere? You and I shall not come to an understanding\nbefore we have given each other a taste of our fists. You beg without\nany sense of decency: are there not feasts elsewhere among the\nAchaeans, as well as here?”\n\nUlysses made no answer, but bowed his head and brooded. Then a third\nman, Philoetius, joined them, who was bringing in a barren heifer and\nsome goats. These were brought over by the boatmen who are there to\ntake people over when any one comes to them. So Philoetius made his\nheifer and his goats secure under the gatehouse, and then went up to\nthe swineherd. “Who, Swineherd,” said he, “is this stranger that is\nlately come here? Is he one of your men? What is his family? Where does\nhe come from? Poor fellow, he looks as if he had been some great man,\nbut the gods give sorrow to whom they will—even to kings if it so\npleases them.”", "model_name": "sentence-transformers/LaBSE", "chunking_name": "paragraph", "chunk_size": 1024, "chunk_overlap": 128}