{"text": "Then the heroes well considered,\nAnd the women gave their counsel,\nHow to kill the magic infant,\nThat their tribe may live in safety.\nIt appeared the boy would prosper;\nFinally, they all consenting,\nHe was placed within a basket,\nAnd with willows firmly fastened,\nTaken to the reeds and rushes,\nLowered to the deepest waters,\nIn his basket there to perish.\n\nWhen three nights had circled over,\nMessengers of Untamoinen\nWent to see if he had perished\nIn his basket in the waters;\nBut the prodigy was living,\nHad not perished in the rushes;\nHe had left his willow-basket,\nSat in triumph on a billow,\nIn his hand a rod of copper,\nOn the rod a golden fish-line,\nFishing for the silver whiting,\nMeasuring the deeps beneath him;\nIn the sea was little water,\nScarcely would it fill three measures.\n\nUntamoinen then reflected,\nThis the language of the wizard:\n“Whither shall we take this wonder,\nLay this prodigy of evil,\nThat destruction may o’ertake him,\nWhere the boy will sink and perish?”", "model_name": "intfloat/e5-large-v2", "chunking_name": "paragraph", "chunk_size": 1024, "chunk_overlap": 128}