{"text": "method and means. For the accomplishment of one’s purpose let, therefore,\nArjuna, the son of Pritha, follow Krishna the foremost of the Yadavas and\nlet Bhima follow Arjuna. Policy and good fortune and might will (then)\nbring about success in a matter requiring valour.’ Vaisampayana\nsaid,--‘Thus addressed by Yudhishthira, the trio Krishna, Arjuna and\nBhima, all possessed of great energy, set out for Magadha attired in the\ngarb of Snataka Brahmanas of resplendent bodies, and blessed by the\nagreeable speeches of friends and relatives. Possessed of superior energy\nand of bodies already like the Sun, the Moon, and the Fire, inflamed with\nwrath at the sad lot of their relative kings, those bodies of theirs\nbecame much more blazing. And the people, beholding Krishna and Arjuna,\nboth of whom had never before been vanquished in battle, with Bhima in\nthe van, all ready to achieve the same task, regarded Jarasandha as\nalready slain. For the illustrious pair (Krishna and Arjuna) were masters\n", "model_name": "sentence-transformers/LaBSE", "chunking_name": "paragraph", "chunk_size": 1024, "chunk_overlap": 128}