{"text": "she hath accepted for her lord this Satyavan of excellent qualities! His\nfather speaketh the truth and his mother also is truthful in her speech.\nAnd it is for this that the Brahmanas have named the son Satyavan. In his\nchildhood he took great delight in horses, and used to make horses of\nclay. And he used also to draw pictures of horses. And for this that\nyouth is sometimes called by the name of Chitraswa.’ The king then asked,\n‘And is prince Satyavan, who is devoted to his father, endued with energy\nand intelligence and forgiveness and courage?’ Narada replied, saying,\n‘In energy Satyavan is like unto the sun, and in wisdom like unto\nVrihaspati! And he is brave like unto the lord of the celestials and\nforgiving like unto the Earth herself!’ Aswapati then said, ‘And is the\nprince Satyavan liberal in gifts and devoted to the Brahmanas? Is he\nhandsome and magnanimous and lovely to behold?’ Narada said, ‘In bestowal\nof gifts according to his power, the mighty son of Dyumatsena is like\n", "model_name": "BAAI/bge-m3", "chunking_name": "paragraph", "chunk_size": 1024, "chunk_overlap": 128}