{"text": "The saint, in glory’s light arrayed,\nIn Pushkar’s wood his dwelling made,\nAnd living there on roots and fruit\nDid penance stern and resolute.\n\nThe king who filled Ayodhyá’s throne,\nBy Ambarísha’s name far known,\nAt that same time, it chanced, began\nA sacrificial rite to plan.\nBut Indra took by force away\nThe charger that the king would slay.\nThe victim lost, the Bráhman sped\nTo Ambarísha’s side, and said:\n“Gone is the steed, O King, and this\nIs due to thee, in care remiss.\nSuch heedless faults will kings destroy\nWho fail to guard what they enjoy.\nThe flaw is desperate: we need\nThe charger, or a man to bleed.\nQuick! bring a man if not the horse,\nThat so the rite may have its course.”", "model_name": "sentence-transformers/LaBSE", "chunking_name": "paragraph", "chunk_size": 1024, "chunk_overlap": 128}