{"text": "Vaisampayana said,--“Saying this, Sakuni cast those dice, and said unto\nYudhishthira, ‘Lo! He hath been won by us.’\n\nYudhishthira said,--“This Sahadeva administereth justice. He hath also\nacquired a reputation for learning in this world. However undeserving he\nmay be to be staked in play, with him as stake I will play, with such a\ndear object as it, indeed, he were not so!”\n\nVaisampayana said,--“Hearing this, Sakuni, ready with the dice, adopting\nfoul means, said unto Yudhishthira, ‘Lo! I have won.’\n\n“Sakuni continued,--‘O king, the sons of Madri, dear unto thee, have both\nbeen won by me. It would seem, however, that Bhimasena and Dhananjaya are\nregarded very much by thee.’\n\n“Yudhishthira said,--‘Wretch! thou actest sinfully in thus seeking to\ncreate disunion amongst us who are all of one heart, disregarding\nmorality.’", "model_name": "sentence-transformers/paraphrase-multilingual-MiniLM-L12-v2", "chunking_name": "paragraph", "chunk_size": 1024, "chunk_overlap": 128}