{"text": "19:8 And there was war again: and David went out, and fought with the\nPhilistines, and slew them with a great slaughter; and they fled from\nhim.\n\n19:9 And the evil spirit from the LORD was upon Saul, as he sat in his\nhouse with his javelin in his hand: and David played with his hand.\n\n19:10 And Saul sought to smite David even to the wall with the\njavelin: but he slipped away out of Saul’s presence, and he smote the\njavelin into the wall: and David fled, and escaped that night.\n\n19:11 Saul also sent messengers unto David’s house, to watch him, and\nto slay him in the morning: and Michal David’s wife told him, saying,\nIf thou save not thy life to night, to morrow thou shalt be slain.\n\n19:12 So Michal let David down through a window: and he went, and\nfled, and escaped.\n\n19:13 And Michal took an image, and laid it in the bed, and put a\npillow of goats’ hair for his bolster, and covered it with a cloth.\n\n19:14 And when Saul sent messengers to take David, she said, He is\nsick.", "model_name": "BAAI/bge-m3", "chunking_name": "paragraph", "chunk_size": 1024, "chunk_overlap": 128}