{"text": "t Or by means of my own wisdom.\n u As did Karûn in particular.1\n x As it happened accordingly: for they were punished with a sore famine\nfor seven years and had the bravest of their warriors cut off at the battle of\nBedr.2\n y To those who sincerely repent and profess his unity: for the sins of\nidolaters will not be forgiven.3\n z See chapter 6, p. 97, note a.\n\n1 See cap. 28, p. 295. 2 Al Beidâwi. 3 See p.\n10, note h.", "model_name": "sentence-transformers/paraphrase-multilingual-MiniLM-L12-v2", "chunking_name": "paragraph", "chunk_size": 1024, "chunk_overlap": 128}