{"text": "94. \"Whatever is ... those gods and goddesses shall bear(?)\n\n95. \"They shall never forget, they shall cleave to the god (?)\n\n96. \"... they shall make bright, they shall make shrines.\n\n97. \"Verily, the decision (concerning) the Black-headed [belongeth to]\nthe gods\n\n98. \"... all our names have they called, he (Marduk) is most holy\n(_elli_)\n\n99. \"... they proclaimed and venerated (?) his names.\n\n100. \"His ... is exceedingly bright, his work is ...\n\n101. \"Marduk, whose father Anu proclaimed [his name] from his birth,\n\n102. \"Who hath set the day at his door ... his going,\n\n103. \"By whose help the storm wind was bound ...\n\n104. \"Delivered the gods his fathers in the time of trouble.\n\n105. \"Verily, the gods have proclaimed his sonship.\n\n106. \"In his bright light let them walk for ever.\n\n107. \"[On] men whom he hath formed, the created things fashioned by\nhis fingers\n\n108. \"He hath imposed the service of the gods, and them he hath set\nfree\n\n109. \"...\n\n110. \"... they looked at him,", "model_name": "sentence-transformers/paraphrase-multilingual-MiniLM-L12-v2", "chunking_name": "paragraph", "chunk_size": 1024, "chunk_overlap": 128}