{"text": "105 The Maruts are the winds, deified in the religion of the Veda like\n other mighty powers and phenomena of nature.\n\n106 A Titan or fiend whose destruction has given Vishṇu one of his\n well-known titles, Mádhava.\n\n107 The garden of Indra.\n\n108 One of the most ancient and popular of the numerous names of Vishṇu.\n The word has been derived in several ways, and may mean _he who\n moved on the (primordial) waters_, or _he who pervades or influences\n men or their thoughts_.\n\n109 The Horse-Sacrifice, just described.\n\n110 To walk round an object keeping the right side towards it is a mark\n of great respect. The Sanskrit word for the observance is\n _pradakshiṇá_, from pra pro, and _daksha_ right, Greek δεξίος, Latin\n dexter, Gaelic deas-il. A similar ceremony is observed by the Gaels.", "model_name": "sentence-transformers/LaBSE", "chunking_name": "paragraph", "chunk_size": 1024, "chunk_overlap": 128}