{"text": "Another account separates the name and makes Nü and Kua brother\nand sister, describing them as the only two human beings in\nexistence. At the creation they were placed at the foot of the K'un-lun\nMountains. Then they prayed, saying, \"If thou, O God, hast sent us to\nbe man and wife, the smoke of our sacrifice will stay in one place;\nbut if not, it will be scattered.\" The smoke remained stationary.\n\nBut though Nü Kua is said to have moulded the first man (or the first\nhuman beings) out of clay, it is to be noted that, being only the\nsuccessor of Fu Hsi, long lines of rulers had preceded her of whom no\naccount is given, and also that, as regards the heavens and the earth\nat least, she is regarded as the repairer and not the creator of them.\n\nHeaven-deaf (T'ien-lung) and Earth-dumb (Ti-ya), the two attendants\nof Wên Ch'ang, the God of Literature (see following chapter), have\nalso been drawn into the cosmogonical net. From their union came the\nheavens and the earth, mankind, and all living things.", "model_name": "intfloat/e5-large-v2", "chunking_name": "paragraph", "chunk_size": 1024, "chunk_overlap": 128}