{"text": "1:5 Your fathers, where are they? and the prophets, do they live for\never? 1:6 But my words and my statutes, which I commanded my servants\nthe prophets, did they not take hold of your fathers? and they\nreturned and said, Like as the LORD of hosts thought to do unto us,\naccording to our ways, and according to our doings, so hath he dealt\nwith us.\n\n1:7 Upon the four and twentieth day of the eleventh month, which is\nthe month Sebat, in the second year of Darius, came the word of the\nLORD unto Zechariah, the son of Berechiah, the son of Iddo the\nprophet, saying, 1:8 I saw by night, and behold a man riding upon a\nred horse, and he stood among the myrtle trees that were in the\nbottom; and behind him were there red horses, speckled, and white.\n\n1:9 Then said I, O my lord, what are these? And the angel that talked\nwith me said unto me, I will shew thee what these be.\n\n1:10 And the man that stood among the myrtle trees answered and said,\nThese are they whom the LORD hath sent to walk to and fro through the\nearth.", "model_name": "sentence-transformers/LaBSE", "chunking_name": "paragraph", "chunk_size": 1024, "chunk_overlap": 128}