{"text": "“Be no longer full of sorrow,\nDry thy tears, thou bride of beauty,\nThou hast found a noble husband,\nBetter wilt thou fare than ever,\nBy the side of Ilmarinen,\nArtist husband, metal-master,\nBread-provider of thy table,\nOn the arm of the fish-catcher,\nOn the breast of the elk-hunter,\nBy the side of the bear-killer.\nThou hast won the best of suitors,\nHast obtained a mighty hero;\nNever idle is his cross-bow,\nOn the nails his quivers hang not,\nNeither are his dogs in kennel,\nActive agents is his hunting.\nThrice within the budding spring-time\nIn the early hours of morning\nHe arises from his fare-couch,\nFrom his slumber in the brush-wood,\nThrice within the sowing season,\nOn his eyes the deer has fallen,\nAnd the branches brushed his vesture,\nAnd his locks been combed by fir-boughs.\nHasten homeward with thy husband,\nWhere thy hero’s friends await thee,\nWhere his forests sing thy welcome.\n\n“Ilmarinen there possesses\nAll the birds that fly in mid-air,\nAll the beasts that haunt the woodlands,\nAll that feed upon the mountains,\nAll that graze on hill and valley,\nSheep and cattle by the thousands;\nSweet the grass upon his meadows,\nSweet the barley in his uplands,\nIn the lowlands corn abundant,\nWheat upon the elm-wood fallows,\nNear the streamlets rye is waving,\nWaving grain on many acres,\nOn his mountains gold and silver,\nRich his mines of shining copper,\nHighlands filled with magic metals,\nChests of jewels in his store-house,\nAll the wealth of Kalevala.”", "model_name": "BAAI/bge-m3", "chunking_name": "paragraph", "chunk_size": 1024, "chunk_overlap": 128}