{"text": "“As he spoke he pulled the herb out of the ground and shewed me what it\nwas like. The root was black, while the flower was as white as milk;\nthe gods call it Moly, and mortal men cannot uproot it, but the gods\ncan do whatever they like.\n\n“Then Mercury went back to high Olympus passing over the wooded island;\nbut I fared onward to the house of Circe, and my heart was clouded with\ncare as I walked along. When I got to the gates I stood there and\ncalled the goddess, and as soon as she heard me she came down, opened\nthe door, and asked me to come in; so I followed her—much troubled in\nmy mind. She set me on a richly decorated seat inlaid with silver,\nthere was a footstool also under my feet, and she mixed a mess in a\ngolden goblet for me to drink; but she drugged it, for she meant me\nmischief. When she had given it me, and I had drunk it without its\ncharming me, she struck me with her wand. ‘There now,’ she cried, ‘be\noff to the pigstye, and make your lair with the rest of them.’", "model_name": "BAAI/bge-m3", "chunking_name": "paragraph", "chunk_size": 1024, "chunk_overlap": 128}