{"text": "“Ashtaka asked, ‘After death, the body is burnt, or otherwise destroyed.\nReduced to nothing upon such dissolution, by what principle is one\nrevived?’ Yayati said, ‘O lion among kings, the person that dies assumes\na subtil form; and retaining consciousness of all his acts as in a dream,\nhe enters some other form with a speed quicker than that of air itself.\nThe virtuous attain to a superior, and the vicious to an inferior form of\nexistence. The vicious become worms and insects. I have nothing more to\nsay, O thou of great and pure soul! I have told thee how beings are born,\nafter development of embryonic forms, as four-footed, six-footed\ncreatures and others with more feet. What more wilt thou ask me?’\n\n“Ashtaka said, ‘How, O father, do men attain to those superior regions\nwhence there is no return to earthly life? Is it by asceticism or by\nknowledge? How also can one gradually attain to felicitous regions? Asked\nby me, O answer it in full.’", "model_name": "intfloat/e5-large-v2", "chunking_name": "paragraph", "chunk_size": 1024, "chunk_overlap": 128}