{"text": "3:20 All go unto one place; all are of the dust, and all turn to dust\nagain.\n\n3:21 Who knoweth the spirit of man that goeth upward, and the spirit\nof the beast that goeth downward to the earth? 3:22 Wherefore I\nperceive that there is nothing better, than that a man should rejoice\nin his own works; for that is his portion: for who shall bring him to\nsee what shall be after him? 4:1 So I returned, and considered all\nthe oppressions that are done under the sun: and behold the tears of\nsuch as were oppressed, and they had no comforter; and on the side of\ntheir oppressors there was power; but they had no comforter.\n\n4:2 Wherefore I praised the dead which are already dead more than the\nliving which are yet alive.\n\n4:3 Yea, better is he than both they, which hath not yet been, who\nhath not seen the evil work that is done under the sun.\n\n4:4 Again, I considered all travail, and every right work, that for\nthis a man is envied of his neighbour. This is also vanity and\nvexation of spirit.", "model_name": "sentence-transformers/LaBSE", "chunking_name": "paragraph", "chunk_size": 1024, "chunk_overlap": 128}