{"text": "【第一章】子曰、太伯其可謂至德也已矣、三以天下讓、民無得而稱焉。\n CHAP. I. The Master said, 'T'ai-po may be said to have\nreached the highest point of virtuous action. Thrice he declined\nthe kingdom, and the people in ignorance of his motives could\nnot express their approbation of his conduct.'\n\n【第二章】【一節】子曰、恭而無禮則勞、慎而無禮則葸、勇而無禮則亂、\n直而無禮則絞。【二節】君子篤於親、則民興於仁、故舊不遺、則民不偷。\n【第三章】曾子有疾、召門弟子曰、啟予\n CHAP. II. 1. The Master said, 'Respectfulness, without the\nrules of propriety, becomes laborious bustle; carefulness,\nwithout the rules of propriety, becomes timidity; boldness,\nwithout the rules of propriety, becomes insubordination;\nstraightforwardness, without the rules of propriety, becomes\nrudeness.\n 2. 'When those who are in high stations perform well all\ntheir duties to their relations, the people are aroused to virtue.\nWhen old friends are not neglected by them, the people are\npreserved from meanness.'\n CHAP. III. The philosopher Tsang being ill, he called to\nhim the disciples of his school, and said, 'Uncover my feet,\nuncover my hands. It is said in the Book of Poetry, \"We should\nbe apprehensive and cautious, as if on the brink of a deep gulf,\nas if treading on thin ice,\" and so have I been. Now and\nhereafter, I know my escape from all injury to my person, O ye,\nmy little children.'", "model_name": "BAAI/bge-m3", "chunking_name": "paragraph", "chunk_size": 1024, "chunk_overlap": 128}