{"text": "“I was trying to come on here, but the gods detained me in Egypt, for\nmy hecatombs had not given them full satisfaction, and the gods are\nvery strict about having their dues. Now off Egypt, about as far as a\nship can sail in a day with a good stiff breeze behind her, there is an\nisland called Pharos—it has a good harbour from which vessels can get\nout into open sea when they have taken in water—and here the gods\nbecalmed me twenty days without so much as a breath of fair wind to\nhelp me forward. We should have run clean out of provisions and my men\nwould have starved, if a goddess had not taken pity upon me and saved\nme in the person of Idothea, daughter to Proteus, the old man of the\nsea, for she had taken a great fancy to me.\n\n“She came to me one day when I was by myself, as I often was, for the\nmen used to go with their barbed hooks, all over the island in the hope\nof catching a fish or two to save them from the pangs of hunger.\n‘Stranger,’ said she, ‘it seems to me that you like starving in this\nway—at any rate it does not greatly trouble you, for you stick here day\nafter day, without even trying to get away though your men are dying by\ninches.’", "model_name": "sentence-transformers/LaBSE", "chunking_name": "paragraph", "chunk_size": 1024, "chunk_overlap": 128}