{"text": "But special counselling he gave\nTo Hanumán the wise and brave:\nTo him on whom his soul relied,\nWith friendly words the monarch cried:\n“O best of Vánars, naught can stay\nBy land or sea thy rapid way,\nWho through the air thy flight canst bend,\nAnd to the Immortals’ home ascend.\nAll realms, I ween, are known to thee\nWith every mountain, lake, and sea.\nIn strength and speed which naught can tire\nThou, worthy rival of thy sire\nThe mighty monarch of the wind,\nWhere’er thou wilt a way canst find.\nExert thy power, O swift and strong,\nBring back the lady lost so long,\nFor time and place, O thou most wise,\nLie open to thy searching eyes.”\n\nWhen Ráma heard that special hest\nTo Hanumán above the rest,\nHe from the monarch’s favour drew\nHope of success and trust anew\nThat he on whom his lord relied,\nIn toil and peril trained and tried,\nWould to a happy issue bring\nThe task commanded by the king.\nHe gave the ring that bore his name,\nA token for the captive dame,\nThat the sad lady in her woe\nThe missive of her lord might know.\n“This ring,” he said, “my wife will see,\nNor fear an envoy sent by me.\nThy valour and thy skill combined,\nThy resolute and vigorous mind,\nAnd King Sugríva’s high behest,\nWith joyful hopes inspire my breast.”", "model_name": "intfloat/e5-large-v2", "chunking_name": "paragraph", "chunk_size": 1024, "chunk_overlap": 128}