{"text": "He ceased: and Ráma answered, while\nPlayed o’er his lips a gracious smile:\n“Not yet convinced? This clear assay\nShall drive each lingering doubt away.”\nThus Ráma spoke his heart to cheer,\nTo Dundubhi’s vast frame drew near:\nHe touched it with his foot in play\nAnd sent it twenty leagues away.\nSugríva marked what easy force\nHurled through the air that demon’s corse\nWhose mighty bones were white and dried,\nAnd to the son of Raghu cried:\n“My brother Báli, when his might\nWas drunk and weary from the fight,\nHurled forth the monster body, fresh\nWith skin and sinews, blood and flesh.\nNow flesh and blood are dried away,\nThe crumbling bones are light as hay,\nWhich thou, O Raghu’s son, hast sent\nFlying through air in merriment.\nThis test alone is weak to show\nIf thou be stronger or the foe.\nBy thee a heap of mouldering bone,\nBy him the recent corse was thrown.\nThy strength, O Prince, is yet untried:\nCome, pierce one tree: let this decide.\nPrepare thy ponderous bow and bring\nClose to thine ear the straining string.\n", "model_name": "sentence-transformers/paraphrase-multilingual-MiniLM-L12-v2", "chunking_name": "paragraph", "chunk_size": 1024, "chunk_overlap": 128}