{"text": "The main arguments on which I base the first of these somewhat\nstartling contentions, have been prominently and repeatedly before the\nEnglish and Italian public ever since they appeared (without rejoinder)\nin the “Athenaeum” for January 30 and February 20, 1892. Both\ncontentions were urged (also without rejoinder) in the Johnian “Eagle”\nfor the Lent and October terms of the same year. Nothing to which I\nshould reply has reached me from any quarter, and knowing how anxiously\nI have endeavoured to learn the existence of any flaws in my argument,\nI begin to feel some confidence that, did such flaws exist, I should\nhave heard, at any rate about some of them, before now. Without,\ntherefore, for a moment pretending to think that scholars generally\nacquiesce in my conclusions, I shall act as thinking them little likely\nso to gainsay me as that it will be incumbent upon me to reply, and\nshall confine myself to translating the “Odyssey” for English readers,\nwith such notes as I think will be found useful. Among these I would\nespecially call attention to one on xxii. 465-473 which Lord Grimthorpe\nhas kindly allowed me to make public.", "model_name": "sentence-transformers/LaBSE", "chunking_name": "paragraph", "chunk_size": 1024, "chunk_overlap": 128}