{"text": "10:3 And the battle went sore against Saul, and the archers hit him,\nand he was wounded of the archers.\n\n10:4 Then said Saul to his armourbearer, Draw thy sword, and thrust me\nthrough therewith; lest these uncircumcised come and abuse me. But his\narmourbearer would not; for he was sore afraid. So Saul took a sword,\nand fell upon it.\n\n10:5 And when his armourbearer saw that Saul was dead, he fell\nlikewise on the sword, and died.\n\n10:6 So Saul died, and his three sons, and all his house died\ntogether.\n\n10:7 And when all the men of Israel that were in the valley saw that\nthey fled, and that Saul and his sons were dead, then they forsook\ntheir cities, and fled: and the Philistines came and dwelt in them.\n\n10:8 And it came to pass on the morrow, when the Philistines came to\nstrip the slain, that they found Saul and his sons fallen in mount\nGilboa.", "model_name": "sentence-transformers/LaBSE", "chunking_name": "paragraph", "chunk_size": 1024, "chunk_overlap": 128}