{"text": " And night, with sable shades, involves his head.”\n “Seek not to know,” the ghost replied with tears,\n “The sorrows of thy sons in future years.\n This youth (the blissful vision of a day)\n Shall just be shown on earth, and snatch’d away.\n The gods too high had rais’d the Roman state,\n Were but their gifts as permanent as great.\n What groans of men shall fill the Martian field!\n How fierce a blaze his flaming pile shall yield!\n What fun’ral pomp shall floating Tiber see,\n When, rising from his bed, he views the sad solemnity!\n No youth shall equal hopes of glory give,\n No youth afford so great a cause to grieve;\n The Trojan honour, and the Roman boast,\n Admir’d when living, and ador’d when lost!\n Mirror of ancient faith in early youth!\n Undaunted worth, inviolable truth!\n No foe, unpunish’d, in the fighting field\n Shall dare thee, foot to foot, with sword and shield;\n Much less in arms oppose thy matchless force,\n When thy sharp spurs shall urge thy foaming horse.\n", "model_name": "sentence-transformers/paraphrase-multilingual-MiniLM-L12-v2", "chunking_name": "paragraph", "chunk_size": 1024, "chunk_overlap": 128}