{"text": "15:26 And Samuel said unto Saul, I will not return with thee: for thou\nhast rejected the word of the LORD, and the LORD hath rejected thee\nfrom being king over Israel.\n\n15:27 And as Samuel turned about to go away, he laid hold upon the\nskirt of his mantle, and it rent.\n\n15:28 And Samuel said unto him, The LORD hath rent the kingdom of\nIsrael from thee this day, and hath given it to a neighbour of thine,\nthat is better than thou.\n\n15:29 And also the Strength of Israel will not lie nor repent: for he\nis not a man, that he should repent.\n\n15:30 Then he said, I have sinned: yet honour me now, I pray thee,\nbefore the elders of my people, and before Israel, and turn again with\nme, that I may worship the LORD thy God.\n\n15:31 So Samuel turned again after Saul; and Saul worshipped the LORD.\n\n15:32 Then said Samuel, Bring ye hither to me Agag the king of the\nAmalekites. And Agag came unto him delicately. And Agag said, Surely\nthe bitterness of death is past.", "model_name": "sentence-transformers/LaBSE", "chunking_name": "paragraph", "chunk_size": 1024, "chunk_overlap": 128}