{"text": " the point of the spear struck against the silver and was turned\n aside as though it had been lead: King Agamemnon caught it from\n his hand, and drew it towards him with the fury of a lion; he\n then drew his sword, and killed Iphidamas by striking him on the\n neck. So there the poor fellow lay, sleeping a sleep as it were\n of bronze, killed in the defence of his fellow-citizens, far from\n his wedded wife, of whom he had had no joy though he had given\n much for her: he had given a hundred head of cattle down, and had\n promised later on to give a thousand sheep and goats mixed, from\n the countless flocks of which he was possessed. Agamemnon son of\n Atreus then despoiled him, and carried off his armour into the\n host of the Achaeans.", "model_name": "sentence-transformers/paraphrase-multilingual-MiniLM-L12-v2", "chunking_name": "paragraph", "chunk_size": 1024, "chunk_overlap": 128}