{"text": "“Thou bringest me,” she cried again,\n“A mingled draught of bliss and pain:\nBliss, that he wears me in his heart,\nPain, that he wakes and weeps apart,\nO, see how Fate is king of all,\nNow lifts us high, now bids us fall,\nAnd leads a captive bound with cord\nThe meanest slave, the proudest lord,\nThus even now Fate’s stern decree\nHas struck with grief my lord and me.\nSay, how shall Ráma reach the shore\nOf sorrow’s waves that rise and roar,\nA shipwrecked sailor, well nigh drowned\nIn the wild sea that foams around?\nWhen will he smite the demon down,\nLay low in dust the giants’ town,\nAnd, glorious from his foes’ defeat,\nHis wife, his long-lost Sítá, meet?\nGo, bid him speed to smite his foes\nBefore the year shall reach its close.\nTen months are fled but two remain,\nThen Rávaṇ’s captive must be slain.\nOft has Vibhishaṇ,(863) just and wise,\nBesought him to restore his prize.\nBut deaf is Rávaṇ’s senseless ear:\nHis brother’s rede he will not hear.\nVibhishaṇ’s daughter(864) loves me well:\n", "model_name": "intfloat/e5-large-v2", "chunking_name": "paragraph", "chunk_size": 1024, "chunk_overlap": 128}