{"text": "section 238. If a boatman has grounded the ship of a man and has\nrefloated her, he shall give money to half her price.\n\nsection 239. If a man has hired a boatman, he shall give him six _GUR_\nof corn per year.\n\nsection 240. If a ship that is going forward has struck a ship at anchor\nand has sunk her, the owner of the ship that has been sunk whatever he\nhas lost in his ship shall recount before God, and that of the ship going\nforward which sunk the ship at anchor shall render to him his ship and\nwhatever of his was lost.\n\nsection 241. If a man has taken an ox on distraint, he shall pay one-\nthird of a mina of silver.\n\nsection 242. If a man has hired a working ox for one year, he shall pay\nfour _GUR_ of corn as its hire.\n\nsection 243. If a milch cow, he shall give three _GUR_ of corn to its\nowner.\n\nsection 244. If a man has hired an ox or sheep and a lion has killed it\nin the open field, that loss is for its owner forsooth.", "model_name": "intfloat/e5-large-v2", "chunking_name": "paragraph", "chunk_size": 1024, "chunk_overlap": 128}