{"text": "107:12 Therefore he brought down their heart with labour; they fell\ndown, and there was none to help.\n\n107:13 Then they cried unto the LORD in their trouble, and he saved\nthem out of their distresses.\n\n107:14 He brought them out of darkness and the shadow of death, and\nbrake their bands in sunder.\n\n107:15 Oh that men would praise the LORD for his goodness, and for his\nwonderful works to the children of men!\n\n107:16 For he hath broken the gates of brass, and cut the bars of iron\nin sunder.\n\n107:17 Fools because of their transgression, and because of their\niniquities, are afflicted.\n\n107:18 Their soul abhorreth all manner of meat; and they draw near\nunto the gates of death.\n\n107:19 Then they cry unto the LORD in their trouble, and he saveth\nthem out of their distresses.\n\n107:20 He sent his word, and healed them, and delivered them from\ntheir destructions.\n\n107:21 Oh that men would praise the LORD for his goodness, and for his\nwonderful works to the children of men!", "model_name": "intfloat/e5-large-v2", "chunking_name": "paragraph", "chunk_size": 1024, "chunk_overlap": 128}