{"text": "And watch some part of the night in the same exercise, as a work of\nsupererogation for thee: peradventure thy LORD will raise thee to an\nhonourable station.t\n And say, O LORD, cause me to enter with a favorable entry, and cause me\nto come forthu with a favorable coming forth; and grant me from thee an\nassisting power.\n And say, Truth is come, and falsehood is vanished: for falsehood is of\nshort continuance.x\n We send down of the Koran that which is a medicine and mercy unto the\ntrue believers; but it shall only increase the perdition of the unjust.\n When we bestow favors on man, he retireth and withdraweth himself\nungratefully from us: but when evil toucheth him, he despaireth of our mercy.\n Say, Every one acteth after his own manner:y but your LORD best knoweth\nwho is most truly directed in his way.\n They will ask thee concerning the spirit:z answer, The spirit was created\nat the command of my LORD:a but ye have no knowledge given unto you, except a\nlittle.b\n", "model_name": "BAAI/bge-m3", "chunking_name": "paragraph", "chunk_size": 1024, "chunk_overlap": 128}