{"text": "whithersoever thou pleasest. This, indeed, is the higher virtue as\ninstanced by men conversant with religion.’ Atri replied, ‘I am informed,\nO virtuous one, by the high-souled Gautama, that Vainya is a pious\nprince, devoted to the cause of truth; but there are Brahmanas (about his\npersons) who are jealous of me; and as Gautama hath told me this, I do\nnot venture to go there, for (while) there, if I were to advise what is\ngood and calculated to secure piety and the fulfilment of one’s desires,\nthey would contradict me with words unproductive of any good. But I\napprove of any counsel and will go there; Vainya will give me kine and\nhoards of riches.’", "model_name": "intfloat/e5-large-v2", "chunking_name": "paragraph", "chunk_size": 1024, "chunk_overlap": 128}