{"text": "7:2 Then a lord on whose hand the king leaned answered the man of God,\nand said, Behold, if the LORD would make windows in heaven, might this\nthing be? And he said, Behold, thou shalt see it with thine eyes, but\nshalt not eat thereof.\n\n7:3 And there were four leprous men at the entering in of the gate:\nand they said one to another, Why sit we here until we die? 7:4 If we\nsay, We will enter into the city, then the famine is in the city, and\nwe shall die there: and if we sit still here, we die also. Now\ntherefore come, and let us fall unto the host of the Syrians: if they\nsave us alive, we shall live; and if they kill us, we shall but die.\n\n7:5 And they rose up in the twilight, to go unto the camp of the\nSyrians: and when they were come to the uttermost part of the camp of\nSyria, behold, there was no man there.", "model_name": "BAAI/bge-m3", "chunking_name": "paragraph", "chunk_size": 1024, "chunk_overlap": 128}