{"text": "23:8 These be the names of the mighty men whom David had: The\nTachmonite that sat in the seat, chief among the captains; the same\nwas Adino the Eznite: he lift up his spear against eight hundred, whom\nhe slew at one time.\n\n23:9 And after him was Eleazar the son of Dodo the Ahohite, one of the\nthree mighty men with David, when they defied the Philistines that\nwere there gathered together to battle, and the men of Israel were\ngone away: 23:10 He arose, and smote the Philistines until his hand\nwas weary, and his hand clave unto the sword: and the LORD wrought a\ngreat victory that day; and the people returned after him only to\nspoil.\n\n23:11 And after him was Shammah the son of Agee the Hararite. And the\nPhilistines were gathered together into a troop, where was a piece of\nground full of lentiles: and the people fled from the Philistines.\n\n23:12 But he stood in the midst of the ground, and defended it, and\nslew the Philistines: and the LORD wrought a great victory.", "model_name": "BAAI/bge-m3", "chunking_name": "paragraph", "chunk_size": 1024, "chunk_overlap": 128}