{"text": "15:23 And they gave him to drink wine mingled with myrrh: but he\nreceived it not.\n\n15:24 And when they had crucified him, they parted his garments,\ncasting lots upon them, what every man should take.\n\n15:25 And it was the third hour, and they crucified him.\n\n15:26 And the superscription of his accusation was written over, THE\nKING OF THE JEWS.\n\n15:27 And with him they crucify two thieves; the one on his right\nhand, and the other on his left.\n\n15:28 And the scripture was fulfilled, which saith, And he was\nnumbered with the transgressors.\n\n15:29 And they that passed by railed on him, wagging their heads, and\nsaying, Ah, thou that destroyest the temple, and buildest it in three\ndays, 15:30 Save thyself, and come down from the cross.\n\n15:31 Likewise also the chief priests mocking said among themselves\nwith the scribes, He saved others; himself he cannot save.\n\n15:32 Let Christ the King of Israel descend now from the cross, that\nwe may see and believe. And they that were crucified with him reviled\nhim.", "model_name": "sentence-transformers/paraphrase-multilingual-MiniLM-L12-v2", "chunking_name": "paragraph", "chunk_size": 1024, "chunk_overlap": 128}