{"text": "32:25 And the children of Gad and the children of Reuben spake unto\nMoses, saying, Thy servants will do as my lord commandeth.\n\n32:26 Our little ones, our wives, our flocks, and all our cattle,\nshall be there in the cities of Gilead: 32:27 But thy servants will\npass over, every man armed for war, before the LORD to battle, as my\nlord saith.\n\n32:28 So concerning them Moses commanded Eleazar the priest, and\nJoshua the son of Nun, and the chief fathers of the tribes of the\nchildren of Israel: 32:29 And Moses said unto them, If the children of\nGad and the children of Reuben will pass with you over Jordan, every\nman armed to battle, before the LORD, and the land shall be subdued\nbefore you; then ye shall give them the land of Gilead for a\npossession: 32:30 But if they will not pass over with you armed, they\nshall have possessions among you in the land of Canaan.\n\n32:31 And the children of Gad and the children of Reuben answered,\nsaying, As the LORD hath said unto thy servants, so will we do.", "model_name": "sentence-transformers/LaBSE", "chunking_name": "paragraph", "chunk_size": 1024, "chunk_overlap": 128}