{"text": "3:2 And next unto him builded the men of Jericho. And next to them\nbuilded Zaccur the son of Imri.\n\n3:3 But the fish gate did the sons of Hassenaah build, who also laid\nthe beams thereof, and set up the doors thereof, the locks thereof,\nand the bars thereof.\n\n3:4 And next unto them repaired Meremoth the son of Urijah, the son of\nKoz. And next unto them repaired Meshullam the son of Berechiah, the\nson of Meshezabeel. And next unto them repaired Zadok the son of\nBaana.\n\n3:5 And next unto them the Tekoites repaired; but their nobles put not\ntheir necks to the work of their LORD.\n\n3:6 Moreover the old gate repaired Jehoiada the son of Paseah, and\nMeshullam the son of Besodeiah; they laid the beams thereof, and set\nup the doors thereof, and the locks thereof, and the bars thereof.\n\n3:7 And next unto them repaired Melatiah the Gibeonite, and Jadon the\nMeronothite, the men of Gibeon, and of Mizpah, unto the throne of the\ngovernor on this side the river.", "model_name": "BAAI/bge-m3", "chunking_name": "paragraph", "chunk_size": 1024, "chunk_overlap": 128}