{"text": "25:1 The word of the LORD came again unto me, saying, 25:2 Son of man,\nset thy face against the Ammonites, and prophesy against them; 25:3\nAnd say unto the Ammonites, Hear the word of the Lord GOD; Thus saith\nthe Lord GOD; Because thou saidst, Aha, against my sanctuary, when it\nwas profaned; and against the land of Israel, when it was desolate;\nand against the house of Judah, when they went into captivity; 25:4\nBehold, therefore I will deliver thee to the men of the east for a\npossession, and they shall set their palaces in thee, and make their\ndwellings in thee: they shall eat thy fruit, and they shall drink thy\nmilk.\n\n25:5 And I will make Rabbah a stable for camels, and the Ammonites a\ncouching place for flocks: and ye shall know that I am the LORD.", "model_name": "sentence-transformers/LaBSE", "chunking_name": "paragraph", "chunk_size": 1024, "chunk_overlap": 128}