{"text": "From his master, Tu O, the celebrated Taoist magician of the K'un-lun\nMountains, Hêng acquired a marvellous power. When he snorted, his\nnostrils, with a sound like that of a bell, emitted two white columns\nof light, which destroyed his enemies, body and soul. Thus through him\nthe Chou gained numerous victories. But one day he was captured, bound,\nand taken to the general of Chou. His life was spared, and he was\nmade general superintendent of army stores as well as generalissimo\nof five army corps. Later on he found himself face to face with the\nBlower. The latter had learnt from the magician how to store in his\nchest a supply of yellow gas which, when he blew it out, annihilated\nanyone whom it struck. By this means he caused large gaps to be made\nin the ranks of the enemy.\n\nBeing opposed to each other, the one snorting out great streaks of\nwhite light, the other blowing streams of yellow gas, the combat\ncontinued until the Blower was wounded in the shoulder by No-cha,\nof the army of Chou, and pierced in the stomach with a spear by Huang\nFei-hu, Yellow Flying Tiger.", "model_name": "BAAI/bge-m3", "chunking_name": "paragraph", "chunk_size": 1024, "chunk_overlap": 128}