{"text": "The damsel’s breast with fury burned:\nShe answered, as the gift she spurned:\n“What time, O simple Queen, is this\nFor idle dreams of fancied bliss?\nHast thou not sense thy state to know,\nEngulfed in seas of whelming woe;\nSick as I am with grief and pain\nMy lips can scarce a laugh restrain\nTo see thee hail with ill-timed joy\nA peril mighty to destroy.\nI mourn for one so fondly blind:\nWhat woman of a prudent mind\nWould welcome, e’en as thou hast done,\nThe lordship of a rival’s son,\nRejoiced to find her secret foe\nEmpowered, like death, to launch the blow;\nI see that Ráma still must fear\nThy Bharat, to his throne too near.\nHence is my heart disquieted,\nFor those who fear are those we dread.\nLakshmaṇ, the mighty bow who draws,\nWith all his soul serves Ráma’s cause;\nAnd chains as strong to Bharat bind\nŚatrughna, with his heart and mind,\nNow next to Ráma, lady fair,\nThy Bharat is the lawful heir:\nAnd far remote, I ween, the chance\nThat might the younger two advance.\nYes, Queen, ’tis Ráma that I dread,\n", "model_name": "intfloat/e5-large-v2", "chunking_name": "paragraph", "chunk_size": 1024, "chunk_overlap": 128}