{"text": "The trenches first they pass’d; then took their way\n Where their proud foes in pitch’d pavilions lay;\n To many fatal, ere themselves were slain.\n They found the careless host dispers’d upon the plain,\n Who, gorg’d, and drunk with wine, supinely snore.\n Unharness’d chariots stand along the shore:\n Amidst the wheels and reins, the goblet by,\n A medley of debauch and war, they lie.\n Observing Nisus shew’d his friend the sight:\n “Behold a conquest gain’d without a fight.\n Occasion offers, and I stand prepar’d;\n There lies our way; be thou upon the guard,\n And look around, while I securely go,\n And hew a passage thro’ the sleeping foe.”\n Softly he spoke; then striding took his way,\n With his drawn sword, where haughty Rhamnes lay;\n His head rais’d high on tapestry beneath,\n And heaving from his breast, he drew his breath;\n A king and prophet, by King Turnus lov’d:\n But fate by prescience cannot be remov’d.\n Him and his sleeping slaves he slew; then spies\n Where Remus, with his rich retinue, lies.\n", "model_name": "intfloat/e5-large-v2", "chunking_name": "paragraph", "chunk_size": 1024, "chunk_overlap": 128}