{"text": "are collected, some suppose it means no more in this passage than the spot or\nfissure whence the first eruption of waters brake forth.\n s Or, as the words may also be rendered, and some commentators think\nthey ought, two pair, that is, two males and two females of each species;\nwherein they partly agree with divers Jewish and Christian writers,1 who from\nthe Hebrew expression, seven and seven and two and two, the male and his\nfemale,2 suppose there went into the ark fourteen pair of every clean, and two\npair of every unclean species. There is a tradition that GOD gathered\ntogether unto Noah all sorts of beasts, birds, and other animals (it being\nindeed difficult to conceive how he should come by them all without some\nsupernatural assistance), and that as he laid hold on them, his right hand\nconstantly fell on the male, and his left on the female.3\n t Namely, thy wife, and thy sons and their wives.4\n u This was an unbelieving son of Noah,5 named Canaan,6 or Yam;7 though\n", "model_name": "intfloat/e5-large-v2", "chunking_name": "paragraph", "chunk_size": 1024, "chunk_overlap": 128}