{"text": "When Sítá heard Kauśalyá’s speech\nHer duty and her gain to teach,\nShe joined her palms with reverent grace\nAnd gave her answer face to face:\n“All will I do, forgetting naught,\nWhich thou, O honoured Queen, hast taught.\nI know, have heard, and deep have stored\nThe rules of duty to my lord.\nNot me, good Queen, shouldst thou include\nAmong the faithless multitude.\nIts own sweet light the moon shall leave\nEre I to duty cease to cleave.\nThe stringless lute gives forth no strain,\nThe wheelless car is urged in vain;\nNo joy a lordless dame, although\nBlest with a hundred sons, can know.\nFrom father, brother, and from son\nA measured share of joy is won:\nWho would not honour, love, and bless\nHer lord, whose gifts are measureless?\nThus trained to think, I hold in awe\nScripture’s command and duty’s law.\nHim can I hold in slight esteem?\nHer lord is woman’s God, I deem.”\nKauśalyá heard the lady’s speech,\nNor failed those words her heart to reach.\nThen, pure in mind, she gave to flow\nThe tear that sprang of joy and woe.\n", "model_name": "sentence-transformers/paraphrase-multilingual-MiniLM-L12-v2", "chunking_name": "paragraph", "chunk_size": 1024, "chunk_overlap": 128}