{"text": "8:2 Then I beheld, and lo a likeness as the appearance of fire: from\nthe appearance of his loins even downward, fire; and from his loins\neven upward, as the appearance of brightness, as the colour of amber.\n\n8:3 And he put forth the form of an hand, and took me by a lock of\nmine head; and the spirit lifted me up between the earth and the\nheaven, and brought me in the visions of God to Jerusalem, to the door\nof the inner gate that looketh toward the north; where was the seat of\nthe image of jealousy, which provoketh to jealousy.\n\n8:4 And, behold, the glory of the God of Israel was there, according\nto the vision that I saw in the plain.\n\n8:5 Then said he unto me, Son of man, lift up thine eyes now the way\ntoward the north. So I lifted up mine eyes the way toward the north,\nand behold northward at the gate of the altar this image of jealousy\nin the entry.", "model_name": "intfloat/e5-large-v2", "chunking_name": "paragraph", "chunk_size": 1024, "chunk_overlap": 128}