{"text": "41. Before long, alas! this body will lie on the earth, despised,\nwithout understanding, like a useless log.\n\n42. Whatever a hater may do to a hater, or an enemy to an enemy, a\nwrongly-directed mind will do us greater mischief.\n\n43. Not a mother, not a father will do so much, nor any other relative;\na well-directed mind will do us greater service.\n\nChapter IV. Flowers\n\n44. Who shall overcome this earth, and the world of Yama (the lord of\nthe departed), and the world of the gods? Who shall find out the plainly\nshown path of virtue, as a clever man finds out the (right) flower?\n\n45. The disciple will overcome the earth, and the world of Yama, and the\nworld of the gods. The disciple will find out the plainly shown path of\nvirtue, as a clever man finds out the (right) flower.\n\n46. He who knows that this body is like froth, and has learnt that it\nis as unsubstantial as a mirage, will break the flower-pointed arrow of\nMara, and never see the king of death.", "model_name": "sentence-transformers/LaBSE", "chunking_name": "paragraph", "chunk_size": 1024, "chunk_overlap": 128}