{"text": "whose steeds had been slain taking this opportunity, descended with\nIndrasena from his chariot and mounted that of Sahadeva. And the two\nwarriors, Kshemankara and Mahamuksha, singling out Nakula, began to pour\non him from both sides a perfect shower of keen-edged arrows. The son of\nMadri, however, succeeded in slaying, with a couple of long shafts, both\nthose warriors who had been pouring on him an arrowy shower--like clouds\nin the rainy season. Suratha, the king of Trigartas, well-versed in\nelephant-charges, approaching the front of Nakula’s chariot, caused it to\nbe dragged by the elephant he rode. But Nakula, little daunted at this,\nleaped out of his chariot, and securing a point of vantage, stood shield\nand sword in hand, immovable as a hill. Thereupon Suratha, wishing to\nslay Nakula at once, urged towards him his huge and infuriate elephant\nwith trunk upraised. But when the beast came near, Nakula with his sword\nsevered from his head both trunk and tusks. And that mail-clad elephant,\n", "model_name": "BAAI/bge-m3", "chunking_name": "paragraph", "chunk_size": 1024, "chunk_overlap": 128}