{"text": "who never can bear such treatment. He, therefore, deserveth to die at\nhands! But what can I do? The king is always overflowing with mercy, and\nthou, too, art constantly putting obstacles in my way from a childish\nsense of virtue!’ Having said these words, Vrikodara, with his\ncrescent-shaped arrow, shaved the hair of the prince’s head, heaving five\ntufts in as many places. Jayadratha uttered not a word at this. Then\nVrikodara, addressing the foe said, ‘If thou wishest to live, listen to\nme. O fool! I shall tell thee the means to attain that wish! In public\nassemblies and in open courts thou must say,--I am the slave of the\nPandavas.--on this condition alone, I will pardon thee thy life! This is\nthe customary rule of conquest on the field of battle.’ Thus addressed\nand treated, king Jayadratha said to the mighty and fierce warrior who\nalways looked awful, ‘Be it so!’ And he was trembling and senseless and\nbegrimed with dust. Then Arjuna and Vrikodara, securing him with chains,\n", "model_name": "sentence-transformers/LaBSE", "chunking_name": "paragraph", "chunk_size": 1024, "chunk_overlap": 128}