{"text": "“On hearing this, Yudhishthira asked, ‘O great Muni, whose sons were\nAsuras called Sunda and Upasunda? Whence arose that dissension amongst\nthem, and why did they slay each other? Whose daughter also was this\nTilottama for whose love the maddened brothers killed each other? Was she\nan Apsara (water nymph) or the daughter of any celestial? O thou whose\nwealth is asceticism, we desire, O Brahmana, to hear in detail everything\nas it happened. Indeed, our curiosity hath become great.’”\n\nSECTION CCXI\n\n(Rajya-labha Parva continued)", "model_name": "intfloat/e5-large-v2", "chunking_name": "paragraph", "chunk_size": 1024, "chunk_overlap": 128}