{"text": "10:22 And he was sad at that saying, and went away grieved: for he had\ngreat possessions.\n\n10:23 And Jesus looked round about, and saith unto his disciples, How\nhardly shall they that have riches enter into the kingdom of God!\n10:24 And the disciples were astonished at his words. But Jesus\nanswereth again, and saith unto them, Children, how hard is it for\nthem that trust in riches to enter into the kingdom of God! 10:25 It\nis easier for a camel to go through the eye of a needle, than for a\nrich man to enter into the kingdom of God.\n\n10:26 And they were astonished out of measure, saying among\nthemselves, Who then can be saved? 10:27 And Jesus looking upon them\nsaith, With men it is impossible, but not with God: for with God all\nthings are possible.\n\n10:28 Then Peter began to say unto him, Lo, we have left all, and have\nfollowed thee.", "model_name": "intfloat/e5-large-v2", "chunking_name": "paragraph", "chunk_size": 1024, "chunk_overlap": 128}